{
  "timestamp": 1758597862.5971372,
  "total_events": 6300,
  "cpu_allocation": {
    "corpus_processor": [
      1,
      2
    ],
    "research_processor": [
      3,
      4
    ],
    "optimization_processor": [
      5,
      6,
      7
    ],
    "validation_processor": [
      8
    ]
  },
  "processors": [
    {
      "name": "corpus_processor",
      "cores": [
        1,
        2
      ],
      "queue_size": 0,
      "events_processed": 5250,
      "total_processing_time": 0.6107597351074219,
      "average_processing_time": 0.00011633518763950893
    },
    {
      "name": "research_processor",
      "cores": [
        3,
        4
      ],
      "queue_size": 0,
      "events_processed": 1050,
      "total_processing_time": 0.11648082733154297,
      "average_processing_time": 0.00011093412126813616
    },
    {
      "name": "optimization_processor",
      "cores": [
        5,
        6,
        7
      ],
      "queue_size": 0,
      "events_processed": 0,
      "total_processing_time": 0,
      "average_processing_time": 0
    },
    {
      "name": "validation_processor",
      "cores": [
        8
      ],
      "queue_size": 0,
      "events_processed": 0,
      "total_processing_time": 0,
      "average_processing_time": 0
    }
  ]
}